LICENSE
MANIFEST.in
README.md
changelog
setup.py
bold_identification/BOLDv4_identification.py
bold_identification/__init__.py
bold_identification/bold_engin.py
bold_identification/logger.py
bold_identification.egg-info/PKG-INFO
bold_identification.egg-info/SOURCES.txt
bold_identification.egg-info/dependency_links.txt
bold_identification.egg-info/entry_points.txt
bold_identification.egg-info/requires.txt
bold_identification.egg-info/top_level.txt
bold_identification/data/COX1.fa
bold_identification/data/ITS.fa
bold_identification/data/matk.fa