Metadata-Version: 2.1
Name: bold-identification
Version: 0.0.22
Summary: To get taxa information of sequences from BOLD system
Home-page: https://github.com/linzhi2013/bold_identification
Author: Guanliang Meng
Author-email: linzhi2012@gmail.com
License: UNKNOWN
Platform: UNKNOWN
Classifier: Development Status :: 3 - Alpha
Classifier: Intended Audience :: Science/Research
Classifier: Topic :: Scientific/Engineering :: Bio-Informatics
Classifier: License :: OSI Approved :: GNU General Public License v3 or later (GPLv3+)
Classifier: Programming Language :: Python :: 3
Classifier: Operating System :: MacOS :: MacOS X
Classifier: Operating System :: Microsoft :: Windows
Classifier: Operating System :: POSIX :: Linux
Requires-Python: >=3.5
